[
    {
        "rank": 1,
        "artist": "Mr.Children",
        "song": "innocent world"
    },
    {
        "rank": 2,
        "artist": "広瀬香美",
        "song": "ロマンスの神様"
    },
    {
        "rank": 3,
        "artist": "篠原涼子 with t.komuro",
        "song": "恋しさと せつなさと 心強さと"
    },
    {
        "rank": 4,
        "artist": "B'z",
        "song": "Don't Leave Me"
    },
    {
        "rank": 5,
        "artist": "中島みゆき",
        "song": "空と君のあいだに/ファイト!"
    },
    {
        "rank": 6,
        "artist": "松任谷由実",
        "song": "Hello, my friend"
    },
    {
        "rank": 7,
        "artist": "trf",
        "song": "Survival dAnce 〜no no cry more〜"
    },
    {
        "rank": 8,
        "artist": "大黒摩季",
        "song": "あなただけ見つめてる"
    },
    {
        "rank": 9,
        "artist": "trf",
        "song": "BOY MEETS GIRL"
    },
    {
        "rank": 10,
        "artist": "WANDS",
        "song": "世界が終るまでは…"
    },
    {
        "rank": 11,
        "artist": "藤井フミヤ",
        "song": "TRUE LOVE"
    },
    {
        "rank": 12,
        "artist": "福山雅治",
        "song": "IT'S ONLY LOVE"
    },
    {
        "rank": 13,
        "artist": "藤谷美和子・大内義昭",
        "song": "愛が生まれた日"
    },
    {
        "rank": 14,
        "artist": "CHAGE & ASKA",
        "song": "HEART/NATURAL/On Your Mark"
    },
    {
        "rank": 15,
        "artist": "Mr.Children",
        "song": "CROSS ROAD"
    },
    {
        "rank": 16,
        "artist": "尾崎豊",
        "song": "OH MY LITTLE GIRL"
    },
    {
        "rank": 17,
        "artist": "中山美穂",
        "song": "ただ泣きたくなるの"
    },
    {
        "rank": 18,
        "artist": "DEEN",
        "song": "瞳そらさないで"
    },
    {
        "rank": 19,
        "artist": "DREAMS COME TRUE",
        "song": "WINTER SONG"
    },
    {
        "rank": 20,
        "artist": "大黒摩季",
        "song": "夏が来る"
    },
    {
        "rank": 21,
        "artist": "TUBE",
        "song": "夏を抱きしめて"
    },
    {
        "rank": 22,
        "artist": "Mr.Children",
        "song": "Tomorrow never knows"
    },
    {
        "rank": 23,
        "artist": "竹内まりや",
        "song": "純愛ラプソディ"
    },
    {
        "rank": 24,
        "artist": "ZARD",
        "song": "この愛に泳ぎ疲れても/Boy"
    },
    {
        "rank": 25,
        "artist": "槇原敬之",
        "song": "SPY"
    },
    {
        "rank": 26,
        "artist": "今井美樹",
        "song": "Miss You"
    },
    {
        "rank": 27,
        "artist": "ZARD",
        "song": "こんなにそばに居るのに"
    },
    {
        "rank": 28,
        "artist": "X JAPAN",
        "song": "Rusty Nail"
    },
    {
        "rank": 29,
        "artist": "前田亘輝",
        "song": "Try Boy,Try Girl"
    },
    {
        "rank": 30,
        "artist": "T-BOLAN",
        "song": "マリア"
    },
    {
        "rank": 31,
        "artist": "大黒摩季",
        "song": "永遠の夢に向かって"
    },
    {
        "rank": 32,
        "artist": "NOKKO",
        "song": "人魚"
    },
    {
        "rank": 33,
        "artist": "SMAP",
        "song": "がんばりましょう"
    },
    {
        "rank": 34,
        "artist": "THE 虎舞竜",
        "song": "ロード 〜第二章"
    },
    {
        "rank": 35,
        "artist": "NOA",
        "song": "今を抱きしめて"
    },
    {
        "rank": 36,
        "artist": "T-BOLAN",
        "song": "LOVE/No.1 Girl"
    },
    {
        "rank": 37,
        "artist": "奥田民生",
        "song": "愛のために"
    },
    {
        "rank": 38,
        "artist": "To Be Continued",
        "song": "君だけを見ていた"
    },
    {
        "rank": 39,
        "artist": "DEEN",
        "song": "永遠をあずけてくれ"
    },
    {
        "rank": 40,
        "artist": "氷室京介",
        "song": "VIRGIN BEAT"
    },
    {
        "rank": 41,
        "artist": "米米CLUB",
        "song": "ア・ブラ・カダ・ブラ"
    },
    {
        "rank": 42,
        "artist": "山根康広",
        "song": "Get Along Together 〜愛を贈りたいから〜 (ニューバージョン)"
    },
    {
        "rank": 43,
        "artist": "DREAMS COME TRUE",
        "song": "WHEREVER YOU ARE"
    },
    {
        "rank": 44,
        "artist": "WANDS",
        "song": "Jumpin' Jack Boy/White Memories"
    },
    {
        "rank": 45,
        "artist": "trf",
        "song": "寒い夜だから…"
    },
    {
        "rank": 46,
        "artist": "ICE BOX",
        "song": "冷たいキス"
    },
    {
        "rank": 47,
        "artist": "松任谷由実",
        "song": "春よ、来い"
    },
    {
        "rank": 48,
        "artist": "大黒摩季",
        "song": "白いGradation"
    },
    {
        "rank": 49,
        "artist": "吉岡秀隆",
        "song": "ラストソング"
    },
    {
        "rank": 50,
        "artist": "X JAPAN",
        "song": "Tears"
    }
]