[
    {
        "rank": 1,
        "artist": "SMAP",
        "song": "世界に一つだけの花"
    },
    {
        "rank": 2,
        "artist": "福山雅治",
        "song": "虹/ひまわり/それがすべてさ"
    },
    {
        "rank": 3,
        "artist": "宇多田ヒカル",
        "song": "COLORS"
    },
    {
        "rank": 4,
        "artist": "森山直太朗",
        "song": "さくら (独唱)"
    },
    {
        "rank": 5,
        "artist": "RUI",
        "song": "月のしずく"
    },
    {
        "rank": 6,
        "artist": "I WiSH",
        "song": "明日への扉"
    },
    {
        "rank": 7,
        "artist": "サザンオールスターズ",
        "song": "涙の海で抱かれたい 〜SEA OF LOVE〜"
    },
    {
        "rank": 8,
        "artist": "浜崎あゆみ",
        "song": "&"
    },
    {
        "rank": 9,
        "artist": "Mr.Children",
        "song": "HERO"
    },
    {
        "rank": 10,
        "artist": "ロードオブメジャー",
        "song": "大切なもの"
    },
    {
        "rank": 11,
        "artist": "中島みゆき",
        "song": "地上の星/ヘッドライト・テールライト"
    },
    {
        "rank": 12,
        "artist": "B'z",
        "song": "IT'S SHOWTIME!!"
    },
    {
        "rank": 13,
        "artist": "一青窈",
        "song": "もらい泣き"
    },
    {
        "rank": 14,
        "artist": "KinKi Kids",
        "song": "薄荷キャンディー"
    },
    {
        "rank": 15,
        "artist": "Every Little Thing",
        "song": "UNTITLED 4 ballads"
    },
    {
        "rank": 16,
        "artist": "EXILE",
        "song": "Breezin' 〜Together〜"
    },
    {
        "rank": 17,
        "artist": "KinKi Kids",
        "song": "永遠のBLOODS"
    },
    {
        "rank": 18,
        "artist": "175R",
        "song": "空に唄えば"
    },
    {
        "rank": 19,
        "artist": "B'z",
        "song": "野性のENERGY"
    },
    {
        "rank": 20,
        "artist": "CHEMISTRY",
        "song": "It Takes Two/SOLID DREAM/MOVE ON"
    },
    {
        "rank": 21,
        "artist": "夏川りみ",
        "song": "涙そうそう"
    },
    {
        "rank": 22,
        "artist": "KinKi Kids",
        "song": "心に夢を君には愛を/ギラ☆ギラ"
    },
    {
        "rank": 23,
        "artist": "サザンオールスターズ",
        "song": "勝手にシンドバッド"
    },
    {
        "rank": 24,
        "artist": "倖田來未",
        "song": "real Emotion/1000の言葉"
    },
    {
        "rank": 25,
        "artist": "稲葉浩志",
        "song": "KI"
    },
    {
        "rank": 26,
        "artist": "氷川きよし",
        "song": "白雲の城"
    },
    {
        "rank": 27,
        "artist": "FLOW",
        "song": "贈る言葉"
    },
    {
        "rank": 28,
        "artist": "ロードオブメジャー",
        "song": "雑走/足跡"
    },
    {
        "rank": 29,
        "artist": "BUMP OF CHICKEN",
        "song": "ロストマン/sailing day"
    },
    {
        "rank": 30,
        "artist": "175R",
        "song": "ハッピーライフ"
    },
    {
        "rank": 31,
        "artist": "光永亮太",
        "song": "Always"
    },
    {
        "rank": 32,
        "artist": "浜崎あゆみ",
        "song": "No way to say"
    },
    {
        "rank": 33,
        "artist": "J-FRIENDS",
        "song": "Love Me All Over"
    },
    {
        "rank": 34,
        "artist": "ポルノグラフィティ",
        "song": "メリッサ"
    },
    {
        "rank": 35,
        "artist": "ORANGE RANGE",
        "song": "上海ハニー"
    },
    {
        "rank": 36,
        "artist": "浜崎あゆみ",
        "song": "forgiveness"
    },
    {
        "rank": 37,
        "artist": "嵐",
        "song": "ハダシの未来/言葉より大切なもの"
    },
    {
        "rank": 38,
        "artist": "V6",
        "song": "Darling"
    },
    {
        "rank": 39,
        "artist": "平井堅",
        "song": "Ring"
    },
    {
        "rank": 40,
        "artist": "玉置成実",
        "song": "Believe"
    },
    {
        "rank": 41,
        "artist": "day after tomorrow",
        "song": "moon gate"
    },
    {
        "rank": 42,
        "artist": "桜庭裕一郎",
        "song": "お前やないと あかんねん"
    },
    {
        "rank": 43,
        "artist": "ケツメイシ",
        "song": "夏の思い出"
    },
    {
        "rank": 44,
        "artist": "平井堅",
        "song": "LIFE is... 〜another story〜"
    },
    {
        "rank": 45,
        "artist": "椎名林檎",
        "song": "茎 (STEM) 〜大名遊ビ編〜"
    },
    {
        "rank": 46,
        "artist": "CHEMISTRY",
        "song": "アシタヘカエル/Us"
    },
    {
        "rank": 47,
        "artist": "中島みゆき",
        "song": "銀の龍の背に乗って"
    },
    {
        "rank": 48,
        "artist": "長渕剛",
        "song": "しあわせになろうよ"
    },
    {
        "rank": 49,
        "artist": "嵐",
        "song": "とまどいながら"
    },
    {
        "rank": 50,
        "artist": "GLAY",
        "song": "BEAUTIFUL DREAMER/STREET LIFE"
    }
]